shadowmodelcache/__init__.py
shadowmodelcache/managers.py
shadowmodelcache/models.py
shadowmodelcache/utils.py
shadowmodelcache-0.1.1.dist-info/licenses/LICENSE.txt
shadowmodelcache-0.1.1.dist-info/METADATA
shadowmodelcache-0.1.1.dist-info/WHEEL
shadowmodelcache-0.1.1.dist-info/top_level.txt
shadowmodelcache-0.1.1.dist-info/RECORD
