Metadata-Version: 2.4
Name: shadowmodelcache
Version: 0.1.1
Summary: High-performance django model cache library.
Home-page: https://github.com/saveychauhan/ShadowModelCache
Author: Sawan Chauhan
Author-email: sav.ey@live.co.uk
License: MIT
Classifier: Development Status :: 3 - Alpha
Classifier: Intended Audience :: Developers
Classifier: Topic :: Software Development :: Libraries
Classifier: Programming Language :: Python :: 3
Classifier: Programming Language :: Python :: 3.6
Classifier: Programming Language :: Python :: 3.7
Classifier: Programming Language :: Python :: 3.8
Classifier: Programming Language :: Python :: 3.9
Classifier: Framework :: Django
Classifier: Framework :: Django :: 4.2
Requires-Python: >=3.6
License-File: LICENSE.txt
Requires-Dist: django>=3.2
Requires-Dist: django-redis
Dynamic: author
Dynamic: author-email
Dynamic: classifier
Dynamic: description
Dynamic: description-content-type
Dynamic: home-page
Dynamic: license
Dynamic: license-file
Dynamic: requires-dist
Dynamic: requires-python
Dynamic: summary
